cm4sys/__init__.py
cm4sys-0.0.0.1.dist-info/METADATA
cm4sys-0.0.0.1.dist-info/WHEEL
cm4sys-0.0.0.1.dist-info/top_level.txt
cm4sys-0.0.0.1.dist-info/RECORD
